six-stubs/METADATA.toml
six-stubs/__init__.pyi
six-stubs/py.typed
six-stubs/moves/BaseHTTPServer.pyi
six-stubs/moves/CGIHTTPServer.pyi
six-stubs/moves/SimpleHTTPServer.pyi
six-stubs/moves/__init__.pyi
six-stubs/moves/_dummy_thread.pyi
six-stubs/moves/_thread.pyi
six-stubs/moves/builtins.pyi
six-stubs/moves/cPickle.pyi
six-stubs/moves/collections_abc.pyi
six-stubs/moves/configparser.pyi
six-stubs/moves/copyreg.pyi
six-stubs/moves/email_mime_base.pyi
six-stubs/moves/email_mime_multipart.pyi
six-stubs/moves/email_mime_nonmultipart.pyi
six-stubs/moves/email_mime_text.pyi
six-stubs/moves/html_entities.pyi
six-stubs/moves/html_parser.pyi
six-stubs/moves/http_client.pyi
six-stubs/moves/http_cookiejar.pyi
six-stubs/moves/http_cookies.pyi
six-stubs/moves/queue.pyi
six-stubs/moves/reprlib.pyi
six-stubs/moves/socketserver.pyi
six-stubs/moves/tkinter.pyi
six-stubs/moves/tkinter_commondialog.pyi
six-stubs/moves/tkinter_constants.pyi
six-stubs/moves/tkinter_dialog.pyi
six-stubs/moves/tkinter_filedialog.pyi
six-stubs/moves/tkinter_tkfiledialog.pyi
six-stubs/moves/tkinter_ttk.pyi
six-stubs/moves/urllib_error.pyi
six-stubs/moves/urllib_parse.pyi
six-stubs/moves/urllib_request.pyi
six-stubs/moves/urllib_response.pyi
six-stubs/moves/urllib_robotparser.pyi
six-stubs/moves/urllib/__init__.pyi
six-stubs/moves/urllib/error.pyi
six-stubs/moves/urllib/parse.pyi
six-stubs/moves/urllib/request.pyi
six-stubs/moves/urllib/response.pyi
six-stubs/moves/urllib/robotparser.pyi
types_six-1.17.0.20250304.dist-info/LICENSE
types_six-1.17.0.20250304.dist-info/METADATA
types_six-1.17.0.20250304.dist-info/WHEEL
types_six-1.17.0.20250304.dist-info/top_level.txt
types_six-1.17.0.20250304.dist-info/RECORD
